ewoksppf/__init__.py
ewoksppf/bindings.py
ewoksppf/engine.py
ewoksppf/ppfrunscript.py
ewoksppf/tests/__init__.py
ewoksppf/tests/conftest.py
ewoksppf/tests/test_examples.py
ewoksppf/tests/test_ppf_end.py
ewoksppf/tests/test_ppf_workflow1.py
ewoksppf/tests/test_ppf_workflow10.py
ewoksppf/tests/test_ppf_workflow11.py
ewoksppf/tests/test_ppf_workflow12.py
ewoksppf/tests/test_ppf_workflow13.py
ewoksppf/tests/test_ppf_workflow14.py
ewoksppf/tests/test_ppf_workflow15.py
ewoksppf/tests/test_ppf_workflow16.py
ewoksppf/tests/test_ppf_workflow17.py
ewoksppf/tests/test_ppf_workflow18.py
ewoksppf/tests/test_ppf_workflow19.py
ewoksppf/tests/test_ppf_workflow2.py
ewoksppf/tests/test_ppf_workflow20.py
ewoksppf/tests/test_ppf_workflow21.py
ewoksppf/tests/test_ppf_workflow22.py
ewoksppf/tests/test_ppf_workflow23.py
ewoksppf/tests/test_ppf_workflow24.py
ewoksppf/tests/test_ppf_workflow3.py
ewoksppf/tests/test_ppf_workflow6.py
ewoksppf/tests/test_ppf_workflow7.py
ewoksppf/tests/test_ppf_workflow8.py
ewoksppf/tests/test_ppf_workflow9.py
ewoksppf/tests/test_workflow_events.py
ewoksppf/tests/test_ppf_actors/__init__.py
ewoksppf/tests/test_ppf_actors/pythonActorAdd.py
ewoksppf/tests/test_ppf_actors/pythonActorAdd2.py
ewoksppf/tests/test_ppf_actors/pythonActorAddA.py
ewoksppf/tests/test_ppf_actors/pythonActorAddA2B.py
ewoksppf/tests/test_ppf_actors/pythonActorAddABC2D.py
ewoksppf/tests/test_ppf_actors/pythonActorAddB.py
ewoksppf/tests/test_ppf_actors/pythonActorAddB2C.py
ewoksppf/tests/test_ppf_actors/pythonActorAddC2D.py
ewoksppf/tests/test_ppf_actors/pythonActorAddWithoutSleep.py
ewoksppf/tests/test_ppf_actors/pythonActorCheck.py
ewoksppf/tests/test_ppf_actors/pythonActorDiamondTest.py
ewoksppf/tests/test_ppf_actors/pythonActorTest.py
ewoksppf/tests/test_ppf_actors/pythonErrorHandlerTest.py
ewoksppf-2.0.1.dist-info/licenses/LICENSE.md
ewoksppf-2.0.1.dist-info/METADATA
ewoksppf-2.0.1.dist-info/WHEEL
ewoksppf-2.0.1.dist-info/entry_points.txt
ewoksppf-2.0.1.dist-info/top_level.txt
ewoksppf-2.0.1.dist-info/RECORD
